aserto/directory/assertion/v3/__init__.py
aserto/directory/assertion/v3/assertion_pb2.py
aserto/directory/assertion/v3/assertion_pb2.pyi
aserto/directory/assertion/v3/assertion_pb2_grpc.py
aserto/directory/assertion/v3/assertion_pb2_grpc.pyi
aserto/directory/common/v3/__init__.py
aserto/directory/common/v3/common_pb2.py
aserto/directory/common/v3/common_pb2.pyi
aserto/directory/common/v3/common_pb2_grpc.py
aserto/directory/common/v3/common_pb2_grpc.pyi
aserto/directory/exporter/v3/__init__.py
aserto/directory/exporter/v3/exporter_pb2.py
aserto/directory/exporter/v3/exporter_pb2.pyi
aserto/directory/exporter/v3/exporter_pb2_grpc.py
aserto/directory/exporter/v3/exporter_pb2_grpc.pyi
aserto/directory/importer/v3/__init__.py
aserto/directory/importer/v3/importer_pb2.py
aserto/directory/importer/v3/importer_pb2.pyi
aserto/directory/importer/v3/importer_pb2_grpc.py
aserto/directory/importer/v3/importer_pb2_grpc.pyi
aserto/directory/model/v3/__init__.py
aserto/directory/model/v3/model_pb2.py
aserto/directory/model/v3/model_pb2.pyi
aserto/directory/model/v3/model_pb2_grpc.py
aserto/directory/model/v3/model_pb2_grpc.pyi
aserto/directory/openapi/v3/__init__.py
aserto/directory/openapi/v3/openapi_pb2.py
aserto/directory/openapi/v3/openapi_pb2.pyi
aserto/directory/openapi/v3/openapi_pb2_grpc.py
aserto/directory/openapi/v3/openapi_pb2_grpc.pyi
aserto/directory/reader/v3/__init__.py
aserto/directory/reader/v3/reader_pb2.py
aserto/directory/reader/v3/reader_pb2.pyi
aserto/directory/reader/v3/reader_pb2_grpc.py
aserto/directory/reader/v3/reader_pb2_grpc.pyi
aserto/directory/schema/v3/__init__.py
aserto/directory/schema/v3/group_pb2.py
aserto/directory/schema/v3/group_pb2.pyi
aserto/directory/schema/v3/group_pb2_grpc.py
aserto/directory/schema/v3/group_pb2_grpc.pyi
aserto/directory/schema/v3/identity_pb2.py
aserto/directory/schema/v3/identity_pb2.pyi
aserto/directory/schema/v3/identity_pb2_grpc.py
aserto/directory/schema/v3/identity_pb2_grpc.pyi
aserto_directory-0.33.8.dist-info/LICENSE
aserto_directory-0.33.8.dist-info/METADATA
aserto_directory-0.33.8.dist-info/WHEEL
aserto_directory-0.33.8.dist-info/RECORD
